arrayfire/__init__.py
arrayfire/algorithm.py
arrayfire/arith.py
arrayfire/array.py
arrayfire/base.py
arrayfire/bcast.py
arrayfire/blas.py
arrayfire/cuda.py
arrayfire/data.py
arrayfire/device.py
arrayfire/features.py
arrayfire/graphics.py
arrayfire/image.py
arrayfire/index.py
arrayfire/interop.py
arrayfire/lapack.py
arrayfire/library.py
arrayfire/ml.py
arrayfire/opencl.py
arrayfire/random.py
arrayfire/signal.py
arrayfire/sparse.py
arrayfire/statistics.py
arrayfire/timer.py
arrayfire/util.py
arrayfire/vision.py
arrayfire-3.8.0.dist-info/LICENSE
arrayfire-3.8.0.dist-info/METADATA
arrayfire-3.8.0.dist-info/WHEEL
arrayfire-3.8.0.dist-info/top_level.txt
arrayfire-3.8.0.dist-info/RECORD
