Metadata-Version: 2.1
Name: arrayfire
Version: 3.8.0
Summary: Python bindings for ArrayFire
Home-page: http://arrayfire.com
Maintainer: ArrayFire
Maintainer-email: technical@arrayfire.com
License: UNKNOWN
Platform: UNKNOWN
Classifier: Programming Language :: Python
Classifier: Programming Language :: Python :: 2.7
Classifier: Programming Language :: Python :: 3
Classifier: Programming Language :: Python :: 3.6
Requires-Dist: scikit-build
